aws_cli_assistant/__init__.py
aws_cli_assistant/http_adapter.py
aws_cli_assistant/license_validator.py
aws_cli_assistant/mcp_server.py
aws_cli_assistant/config/__init__.py
aws_cli_assistant/config/defaults.json
aws_cli_assistant/config/secrets.py
aws_cli_assistant/config/settings.py
aws_cli_assistant/core/__init__.py
aws_cli_assistant/core/aws_validator.py
aws_cli_assistant/core/command_generator.py
aws_cli_assistant/core/exceptions.py
aws_cli_assistant/core/nlp_utils.py
aws_cli_assistant/core/telemetry.py
aws_cli_assistant/core/aws_parsers/__init__.py
aws_cli_assistant/core/aws_parsers/dynamodb_parser.py
aws_cli_assistant/core/aws_parsers/ec2_parser.py
aws_cli_assistant/core/aws_parsers/iam_parser.py
aws_cli_assistant/core/aws_parsers/lambda_parser.py
aws_cli_assistant/core/aws_parsers/s3_parser.py
aws_cli_assistant/utils/__init__.py
aws_cli_assistant/utils/constants.py
aws_cli_assistant/utils/logger.py
aws_cli_assistant_lite-1.0.1.dist-info/licenses/LICENSE
scripts/__init__.py
scripts/activate_license.py
scripts/test_phase3.py
scripts/verify_installation.py
tests/__init__.py
tests/test_command_generator.py
tests/test_http_adapter.py
tests/test_mcp_server.py
tests/test_nlp_utils.py
aws_cli_assistant_lite-1.0.1.dist-info/METADATA
aws_cli_assistant_lite-1.0.1.dist-info/WHEEL
aws_cli_assistant_lite-1.0.1.dist-info/entry_points.txt
aws_cli_assistant_lite-1.0.1.dist-info/top_level.txt
aws_cli_assistant_lite-1.0.1.dist-info/RECORD
