Metadata-Version: 2.4
Name: aws-cli-assistant-lite
Version: 1.0.1
Summary: Natural language to AWS CLI converter with real-time validation
Home-page: https://github.com/maliniagrawal/aws-cli-assistant-lite
Author: Malini Agrawal
Author-email: Malini Agrawal <aws2minutes@gmail.com>
License: Commercial
Project-URL: Homepage, https://github.com/maliniagrawal/aws-cli-assistant-lite
Project-URL: Documentation, https://docs.yourdomain.com
Project-URL: Repository, https://github.com/maliniagrawal/aws-cli-assistant-lite
Classifier: Development Status :: 4 - Beta
Classifier: Intended Audience :: Developers
Classifier: License :: Other/Proprietary License
Classifier: Programming Language :: Python :: 3.10
Classifier: Programming Language :: Python :: 3.11
Requires-Python: >=3.10
License-File: LICENSE
Requires-Dist: fastmcp>=0.2.0
Requires-Dist: pydantic>=2.12.0
Requires-Dist: loguru>=0.7.0
Requires-Dist: boto3>=1.40.0
Requires-Dist: botocore>=1.40.0
Requires-Dist: fastapi>=0.115.0
Requires-Dist: uvicorn>=0.32.0
Requires-Dist: transformers>=4.57.0
Requires-Dist: torch>=2.5.0
Requires-Dist: anthropic>=0.70.0
Requires-Dist: python-dotenv>=1.2.0
Dynamic: author
Dynamic: home-page
Dynamic: license-file
Dynamic: requires-python
